web_article_extractor/__init__.py
web_article_extractor/cli.py
web_article_extractor/config.py
web_article_extractor/exceptions.py
web_article_extractor/extractor.py
web_article_extractor/logger.py
web_article_extractor/models.py
web_article_extractor/providers/__init__.py
web_article_extractor/providers/base.py
web_article_extractor/providers/gemini.py
web_article_extractor-1.1.3.dist-info/licenses/LICENSE
web_article_extractor-1.1.3.dist-info/METADATA
web_article_extractor-1.1.3.dist-info/WHEEL
web_article_extractor-1.1.3.dist-info/entry_points.txt
web_article_extractor-1.1.3.dist-info/top_level.txt
web_article_extractor-1.1.3.dist-info/RECORD
