Metadata-Version: 2.4
Name: web-article-extractor
Version: 1.1.3
Summary: A generic module for extracting text and dates from web articles
Author-email: Biagio Frusteri <spaziovettoriale@gmail.com>
License: MIT
Keywords: web-scraping,article-extraction,llm,gemini
Classifier: Development Status :: 3 - Alpha
Classifier: Intended Audience :: Developers
Classifier: License :: OSI Approved :: MIT License
Classifier: Programming Language :: Python :: 3
Classifier: Programming Language :: Python :: 3.11
Classifier: Programming Language :: Python :: 3.12
Classifier: Programming Language :: Python :: 3.13
Requires-Python: >=3.11
License-File: LICENSE
Requires-Dist: google-generativeai>=0.8.0
Requires-Dist: newspaper3k>=0.2.8
Requires-Dist: trafilatura>=1.12.0
Requires-Dist: pyyaml>=6.0.1
Requires-Dist: pydantic>=2.6.0
Requires-Dist: pydantic-settings>=2.1.0
Requires-Dist: pandas>=2.2.0
Requires-Dist: requests>=2.31.0
Requires-Dist: click>=8.1.7
Requires-Dist: python-json-logger>=2.0.7
Requires-Dist: python-dateutil>=2.9.0
Requires-Dist: python-dotenv>=1.0.0
Provides-Extra: dev
Requires-Dist: pytest>=8.0.0; extra == "dev"
Requires-Dist: pytest-cov>=4.1.0; extra == "dev"
Requires-Dist: pytest-mock>=3.12.0; extra == "dev"
Requires-Dist: coverage>=7.4.0; extra == "dev"
Requires-Dist: black>=24.0.0; extra == "dev"
Requires-Dist: isort>=5.13.0; extra == "dev"
Requires-Dist: pylint>=3.0.0; extra == "dev"
Requires-Dist: pre-commit>=3.6.0; extra == "dev"
Requires-Dist: pyupgrade>=3.15.0; extra == "dev"
Requires-Dist: build>=1.0.0; extra == "dev"
Requires-Dist: twine>=5.0.0; extra == "dev"
Dynamic: license-file
